{
  "version": "3",
  "templates": [
    {
      "id": 1,
      "type": 3,
      "title": "Traefik Proxy",
      "name": "traefik",
      "description": "Traefik Proxy with dashboard and whoami service",
      "note": "Deploys a Traefik instance with dashboard and whoami service.",
      "categories": ["Proxy", "Networking"],
      "platform": "linux",
      "logo": "https://raw.githubusercontent.com/devicons/devicon/refs/heads/master/icons/traefikproxy/traefikproxy-original.svg",
      "repository": {
        "url": "https://github.com/chilltemp/network-config",
        "stackfile": "traefik/docker-compose.yml"
      },
      "env": {
        "CLOUDFLARE_DNS_API_TOKEN": "Cloudflare API Token with DNS edit permissions for the DOMAIN",
        "CLOUDFLARE_EMAIL": "Email address associated with the Cloudflare API Token",
        "DOMAIN": "The domain for the host (e.g., example.com)",
        "FQDN": "The fully qualified domain name for the host (e.g., server.example.com becomes...)\n * proxy.server.example.com for accessing the Traefik dashboard\n * whoami.server.example.com for accessing the Whoami test service ",
        "HOST_DATA_PATH": "(optional) Path on the host where Traefik data will be stored (default: /data/traefik)",
        "HOSTNAME": "The hostname for the host (e.g., server.local becomes...)\n * proxy.server.local for accessing the Traefik dashboard\n * whoami.server.local for accessing the Whoami test service "
      }
    }
  ]
}
